pycorpus/__init__.py
pycorpus-2.3.dist-info/WHEEL
pycorpus-2.3.dist-info/METADATA
pycorpus-2.3.dist-info/RECORD
