Metadata-Version: 2.1
Name: pycorpus
Version: 2.3
Summary: Easy concurrent launch of series of file based experiments.
Home-page: https://github.com/josubg/pycorpus/
License: MIT
Keywords: corpus
Author: Josu Bermudez
Author-email: josubg@gmail.com
Requires-Python: >=3.8,<4.0
Classifier: Development Status :: 4 - Beta
Classifier: Intended Audience :: Developers
Classifier: Intended Audience :: Science/Research
Classifier: License :: OSI Approved :: Apache Software License
Classifier: License :: OSI Approved :: MIT License
Classifier: Programming Language :: Python :: 3
Classifier: Programming Language :: Python :: 3.8
Classifier: Programming Language :: Python :: 3.9
Classifier: Topic :: Software Development :: Libraries :: Python Modules
Requires-Dist: lxml (>=4.6.3,<5.0.0)
Project-URL: Repository, https://github.com/josubg/pycorpus/
